marklassian/__init__.py
marklassian/converter.py
marklassian/types.py
marklassian-0.1.0.dist-info/METADATA
marklassian-0.1.0.dist-info/WHEEL
marklassian-0.1.0.dist-info/licenses/LICENSE
marklassian-0.1.0.dist-info/RECORD
