Metadata-Version: 2.4
Name: marklassian
Version: 0.1.0
Summary: Convert Markdown to Atlassian Document Format (ADF)
Project-URL: Homepage, https://github.com/mbroton/marklassian-py
Project-URL: Repository, https://github.com/mbroton/marklassian-py
Author-email: Michał Brotoń <michal@broton.dev>
License-Expression: MIT
License-File: LICENSE
Keywords: adf,atlassian,confluence,jira,markdown
Classifier: Development Status :: 4 - Beta
Classifier: Intended Audience :: Developers
Classifier: License :: OSI Approved :: MIT License
Classifier: Programming Language :: Python :: 3
Classifier: Programming Language :: Python :: 3.10
Classifier: Programming Language :: Python :: 3.11
Classifier: Programming Language :: Python :: 3.12
Classifier: Programming Language :: Python :: 3.13
Classifier: Topic :: Text Processing :: Markup :: Markdown
Requires-Python: >=3.10
Requires-Dist: mistune>=3.0.0
